[{"__symbolic":"module","version":3,"metadata":{"JournalService":{"__symbolic":"class","decorators":[{"__symbolic":"call","expression":{"__symbolic":"reference","module":"@angular/core","name":"Injectable"}}],"members":{"journal":[{"__symbolic":"method"}],"oneEntry":[{"__symbolic":"method"}],"allEntries":[{"__symbolic":"method"}],"addEntry":[{"__symbolic":"method"}],"updateEntry":[{"__symbolic":"method"}],"addJournal":[{"__symbolic":"method"}],"allJournals":[{"__symbolic":"method"}],"__ctor__":[{"__symbolic":"constructor","parameters":[{"__symbolic":"reference","module":"@angular/http","name":"Http"}]}]}}}},{"__symbolic":"module","version":1,"metadata":{"JournalService":{"__symbolic":"class","decorators":[{"__symbolic":"call","expression":{"__symbolic":"reference","module":"@angular/core","name":"Injectable"}}],"members":{"journal":[{"__symbolic":"method"}],"oneEntry":[{"__symbolic":"method"}],"allEntries":[{"__symbolic":"method"}],"addEntry":[{"__symbolic":"method"}],"updateEntry":[{"__symbolic":"method"}],"addJournal":[{"__symbolic":"method"}],"allJournals":[{"__symbolic":"method"}],"__ctor__":[{"__symbolic":"constructor","parameters":[{"__symbolic":"reference","module":"@angular/http","name":"Http"}]}]}}}}]